dwarf_assembly_bias/__init__.py
dwarf_assembly_bias/clustering.py
dwarf_assembly_bias/config.py
dwarf_assembly_bias/elucid_cv.py
dwarf_assembly_bias/obs_catalogs.py
dwarf_assembly_bias/optim.py
dwarf_assembly_bias/sample.py
dwarf_assembly_bias/sample_cosmic_web.py
dwarf_assembly_bias/data/__init__.py
dwarf_assembly_bias/data/sim_elucid.py
dwarf_assembly_bias/samples/__init__.py
dwarf_assembly_bias/samples/field.py
dwarf_assembly_bias/samples/galaxy.py
dwarf_assembly_bias/samples/model_dumper.py
dwarf_assembly_bias/sidm/__init__.py
dwarf_assembly_bias/sidm/drivers.py
dwarf_assembly_bias/sidm/models.py
dwarf_assembly_bias/sidm/profiles.py
dwarf_assembly_bias/sidm/size.py
dwarf_assembly_bias/sidm/jiang22/__init__.py
dwarf_assembly_bias/sidm/jiang22/aux.py
dwarf_assembly_bias/sidm/jiang22/config.py
dwarf_assembly_bias/sidm/jiang22/cosmo.py
dwarf_assembly_bias/sidm/jiang22/galhalo.py
dwarf_assembly_bias/sidm/jiang22/profiles.py
dwarf_assembly_bias/statistics/__init__.py
dwarf_assembly_bias/statistics/cosmic_web.py
dwarf_assembly_bias/utils/__init__.py
dwarf_assembly_bias/utils/gal_web_cor.py
dwarf_assembly_bias/utils/gal_wp.py
dwarf_assembly_bias/utils/stats.py
dwarf_assembly_bias/utils/weights.py
dwarf_assembly_bias-0.0.2.dist-info/licenses/LICENSE
dwarf_assembly_bias-0.0.2.dist-info/METADATA
dwarf_assembly_bias-0.0.2.dist-info/WHEEL
dwarf_assembly_bias-0.0.2.dist-info/top_level.txt
dwarf_assembly_bias-0.0.2.dist-info/RECORD
