Metadata-Version: 2.4
Name: dwarf-assembly-bias
Version: 0.0.2
Summary: Codes for the paper: Unexpected clustering pattern in dwarf galaxies challenges formation models
Author-email: Ziwen Zhang <ziwen@mail.ustc.edu.cn>, Yangyao Chen <yangyaochen.astro@foxmail.com>, Yu Rong <rongyua@ustc.edu.cn>, Huiyuan Wang <whywang@ustc.edu.cn>
Project-URL: Repository, https://github.com/ChenYangyao/dwarf_assembly_bias.git
Classifier: Programming Language :: Python :: 3
Classifier: License :: OSI Approved :: MIT License
Classifier: Operating System :: OS Independent
Requires-Python: >=3.11
License-File: LICENSE
Requires-Dist: pyhipp>=0.3.5
Requires-Dist: pyhipp-sims
Requires-Dist: flake8
Requires-Dist: pytest>=7.0.0
Requires-Dist: elucid
Dynamic: license-file
